DNSPodX/__init__.py
DNSPodX/__version__.py
DNSPodX/domain.py
DNSPodX/record.py
DNSPodX/user.py
DNSPodX/util.py
DNSPodX-0.0.1.dist-info/LICENSE
DNSPodX-0.0.1.dist-info/METADATA
DNSPodX-0.0.1.dist-info/WHEEL
DNSPodX-0.0.1.dist-info/top_level.txt
DNSPodX-0.0.1.dist-info/RECORD
