Metadata-Version: 2.1
Name: DNSPodX
Version: 0.0.1
Summary: DNSPod API v4.6
Home-page: https://github.com/wolfbolin/DNSPodX
Author: WolfBolin
Author-email: mailto@wolfbolin.com
License: MIT
Platform: UNKNOWN
Classifier: License :: OSI Approved :: MIT License
Classifier: Programming Language :: Python
Classifier: Programming Language :: Python :: 3
Classifier: Programming Language :: Python :: 3.6
Classifier: Programming Language :: Python :: Implementation :: CPython
Classifier: Programming Language :: Python :: Implementation :: PyPy
Requires-Python: >=3.6.0
Requires-Dist: requests
